<?xml version="1.0" encoding="UTF-8"?>
<!DOCTYPE suite SYSTEM "https://testng.org/testng-1.0.dtd">
<suite name="Suite">
	<listeners>
		<listener class-name="com.obsquara.testscripts.Listeners" />
	</listeners>
	<test thread-count="5" name="Chrome Test">
		<parameter name="browser" value="chrome" />
		<parameter name="username" value="admin" />
		<parameter name="password" value="admin" />
		<groups>
			<run>
				<include name="smoke" />

			</run>
		</groups>
		<classes>
			<class name="com.obsquara.testscripts.LoginPageDemoTest" />
			<class name="com.obsquara.testscripts.HomePageTest" />
			<class name="com.obsquara.testscripts.ExpenseCategoryTest" />
			<class name="com.obsquara.testscripts.ManageDeliveryBoyTest" />
			<class name="com.obsquara.testscripts.PushNotificationTest" />
			<class name="com.obsquara.testscripts.SettingTest" />
			<class name="com.obsquara.testscripts.AdminUserTest" />
			<class name="com.obsquara.testscripts.ManageUserTest" />
			<class name="com.obsquara.testscripts.ManageSliderTest" />
		</classes>
	</test> <!-- Test -->


</suite> <!-- Suite -->
	
		
		

	